manage.py
drive/__init__.py
drive/asgi.py
drive/settings.py
drive/urls.py
drive/wsgi.py
sample_app/init.py
sample_app/run.py
userface/__init__.py
userface/admin.py
userface/apps.py
userface/forms.py
userface/models.py
userface/tests.py
userface/urls.py
userface/views.py
userface/templates/base_generic.html
userface/templates/css/bootstrap.min.css
userface/templates/css/style.css
userface/templates/css/bootstrap/_media.css
userface/templates/css/bootstrap/utilities/_stretched-link.css
userface/templates/registration/logged_out.html
userface/templates/registration/login.html
userface/templates/registration/register.html
userface/templates/userface/addspot.html
userface/templates/userface/adminportal.html
userface/templates/userface/book.html
userface/templates/userface/confirm.html
userface/templates/userface/cover.html
userface/templates/userface/index.html
userface/templates/userface/parking_spot_list.html
userface/templates/userface/register_vehicle.html
userface/templates/userface/search.html
userface/templates/userface/search_base.html
userface/templates/userface/user_vehicle_list.html
driveways-0.1.2.dist-info/LICENSE.txt
driveways-0.1.2.dist-info/METADATA
driveways-0.1.2.dist-info/WHEEL
driveways-0.1.2.dist-info/entry_points.txt
driveways-0.1.2.dist-info/top_level.txt
driveways-0.1.2.dist-info/RECORD
